ipython_tempmagic-0.0.1.dist-info/DESCRIPTION.rst
ipython_tempmagic-0.0.1.dist-info/METADATA
ipython_tempmagic-0.0.1.dist-info/RECORD
ipython_tempmagic-0.0.1.dist-info/WHEEL
ipython_tempmagic-0.0.1.dist-info/metadata.json
ipython_tempmagic-0.0.1.dist-info/top_level.txt
tempmagic/__init__.py
tempmagic/tempmagic.py
