Metadata-Version: 2.0
Name: ipython-tempmagic
Version: 0.0.1
Summary: Temporary file magic IPython
Home-page: https://github.com/tkf/ipython-tempmagic
Author: Liam Deacon
Author-email: liam.m.deacon@gmail.com
License: UNKNOWN
Keywords: ipython jupyter notebook tempfile tempdir
Platform: UNKNOWN
Classifier: Topic :: Text Processing :: Markup :: HTML
Classifier: Programming Language :: Python :: 2
Classifier: Programming Language :: Python :: 2.7
Classifier: Programming Language :: Python :: 3
Classifier: Programming Language :: Python :: 3.3
Classifier: Programming Language :: Python :: 3.4
Classifier: Programming Language :: Python :: 3.5
Requires-Dist: jupyter (>=1.0.0)
